{
	"timestamp": "2025-05-17T19:14:55.103406+00:00",
	"data": [
		{
			"playerId": "6148530",
			"username": "Laika",
			"stat": 8925,
			"lastSeen": "2025-05-16T11:27:45.374615+00:00",
			"change": 0
		},
		{
			"playerId": "20645553",
			"username": "999",
			"stat": 439,
			"lastSeen": "2025-05-16T05:34:09.202297+00:00",
			"change": 0
		},
		{
			"playerId": "8899024",
			"username": "PurpleSpaceBaboon",
			"stat": 397,
			"lastSeen": "2025-05-16T02:35:00.137564+00:00",
			"change": 0
		},
		{
			"playerId": "20734175",
			"username": "Aqualuka",
			"stat": 338,
			"lastSeen": "2025-05-15T15:01:36.485983+00:00",
			"change": 0
		},
		{
			"playerId": "18418846",
			"username": "pakkiller",
			"stat": 313,
			"lastSeen": "2025-05-15T12:03:09.390123+00:00",
			"change": 0
		},
		{
			"playerId": "20728377",
			"username": "Angus",
			"stat": 254,
			"lastSeen": "2025-05-16T05:18:00.375038+00:00",
			"change": 0
		},
		{
			"playerId": "20666777",
			"username": "Invincible",
			"stat": 251,
			"lastSeen": "2025-05-15T17:50:09.452027+00:00",
			"change": 0
		},
		{
			"playerId": "17120874",
			"username": "Kobi",
			"stat": 228,
			"lastSeen": "2025-05-16T05:46:09.133920+00:00",
			"change": 0
		},
		{
			"playerId": "20704313",
			"username": "XxnoobxX",
			"stat": 226,
			"lastSeen": "2025-05-14T23:19:27.133477+00:00",
			"change": 0
		},
		{
			"playerId": "944643",
			"username": "meemee",
			"stat": 217,
			"lastSeen": "2025-05-15T09:57:36.360585+00:00",
			"change": 0
		},
		{
			"playerId": "5216748",
			"username": "RAMISHNEVERGIVEUP",
			"stat": 209,
			"lastSeen": "2025-05-16T08:24:45.378711+00:00",
			"change": 0
		},
		{
			"playerId": "20691693",
			"username": "thetankcrusher",
			"stat": 208,
			"lastSeen": "2025-05-16T09:32:27.374040+00:00",
			"change": 0
		},
		{
			"playerId": "18625144",
			"username": "Orc-T72",
			"stat": 186,
			"lastSeen": "2025-05-16T02:54:18.141426+00:00",
			"change": 0
		},
		{
			"playerId": "20483828",
			"username": "HonestDiscoJedi",
			"stat": 180,
			"lastSeen": "2025-05-16T09:57:09.367065+00:00",
			"change": 0
		},
		{
			"playerId": "20004968",
			"username": "NeatBlastTomato",
			"stat": 179,
			"lastSeen": "2025-05-16T11:27:36.122154+00:00",
			"change": 0
		},
		{
			"playerId": "17952380",
			"username": "mousemickey",
			"stat": 169,
			"lastSeen": "2025-05-14T22:27:00.140036+00:00",
			"change": 0
		},
		{
			"playerId": "20549294",
			"username": "ImTrAsHh",
			"stat": 166,
			"lastSeen": "2025-05-16T03:46:09.138931+00:00",
			"change": 0
		},
		{
			"playerId": "20730047",
			"username": "Xheiiyne",
			"stat": 161,
			"lastSeen": "2025-05-16T08:58:09.371596+00:00",
			"change": 0
		},
		{
			"playerId": "13773720",
			"username": "Hafiz-Muhammad",
			"stat": 157,
			"lastSeen": "2025-05-16T11:26:09.371948+00:00",
			"change": 0
		},
		{
			"playerId": "19912309",
			"username": "ScruffyBoogieRam",
			"stat": 156,
			"lastSeen": "2025-05-16T10:22:00.371291+00:00",
			"change": 0
		},
		{
			"playerId": "9311306",
			"username": "MegaSquid",
			"stat": 150,
			"lastSeen": "2025-05-16T11:27:45.374615+00:00",
			"change": 0
		},
		{
			"playerId": "19458546",
			"username": "keraunoskiller",
			"stat": 142,
			"lastSeen": "2025-05-16T04:23:45.367774+00:00",
			"change": 0
		},
		{
			"playerId": "15164705",
			"username": "Glitter56371",
			"stat": 140,
			"lastSeen": "2025-05-15T19:42:00.131293+00:00",
			"change": 0
		},
		{
			"playerId": "14623360",
			"username": "HairyLightningElf",
			"stat": 139,
			"lastSeen": "2025-05-15T08:45:45.066608+00:00",
			"change": 0
		},
		{
			"playerId": "16092601",
			"username": "fyrenado",
			"stat": 139,
			"lastSeen": "2025-05-16T04:21:27.198049+00:00",
			"change": 0
		},
		{
			"playerId": "17149251",
			"username": "SmellMySocks",
			"stat": 138,
			"lastSeen": "2025-05-15T18:15:54.157648+00:00",
			"change": 0
		},
		{
			"playerId": "16717384",
			"username": "MATTSUN12255646",
			"stat": 132,
			"lastSeen": "2025-05-15T20:56:18.128234+00:00",
			"change": 0
		},
		{
			"playerId": "20719116",
			"username": "LoneMysteryGolem",
			"stat": 132,
			"lastSeen": "2025-05-15T17:55:45.148741+00:00",
			"change": 0
		},
		{
			"playerId": "20741435",
			"username": "blackhacker",
			"stat": 131,
			"lastSeen": "2025-05-15T14:30:09.137045+00:00",
			"change": 0
		},
		{
			"playerId": "20274169",
			"username": "org",
			"stat": 127,
			"lastSeen": "2025-05-16T03:46:09.138931+00:00",
			"change": 0
		},
		{
			"playerId": "18108574",
			"username": "ffgr",
			"stat": 125,
			"lastSeen": "2025-05-16T10:58:54.367281+00:00",
			"change": 0
		},
		{
			"playerId": "19571311",
			"username": "notdodger",
			"stat": 125,
			"lastSeen": "2025-05-13T01:50:18.713823+00:00",
			"change": 0
		},
		{
			"playerId": "20060899",
			"username": "GrandCosmicAnt",
			"stat": 123,
			"lastSeen": "2025-05-16T10:02:09.366687+00:00",
			"change": 0
		},
		{
			"playerId": "19635407",
			"username": "Mashin",
			"stat": 122,
			"lastSeen": "2025-05-15T19:38:09.126033+00:00",
			"change": 0
		},
		{
			"playerId": "19691813",
			"username": "Jhxjan",
			"stat": 117,
			"lastSeen": "2025-05-16T01:41:45.119394+00:00",
			"change": 0
		},
		{
			"playerId": "20643345",
			"username": "Musa_027",
			"stat": 116,
			"lastSeen": "2025-05-15T16:22:09.121108+00:00",
			"change": 0
		},
		{
			"playerId": "16596741",
			"username": "RawWarWarrior",
			"stat": 115,
			"lastSeen": "2025-05-15T21:47:09.121812+00:00",
			"change": 0
		},
		{
			"playerId": "19481849",
			"username": "Interlude",
			"stat": 114,
			"lastSeen": "2025-05-15T05:21:36.132115+00:00",
			"change": 0
		},
		{
			"playerId": "4916090",
			"username": "Zys",
			"stat": 114,
			"lastSeen": "2025-05-15T23:33:00.126312+00:00",
			"change": 0
		},
		{
			"playerId": "20269995",
			"username": "Giffgaff224",
			"stat": 113,
			"lastSeen": "2025-05-16T11:04:09.132017+00:00",
			"change": 0
		},
		{
			"playerId": "20553075",
			"username": "AHMAD11",
			"stat": 110,
			"lastSeen": "2025-05-16T09:57:09.367065+00:00",
			"change": 0
		},
		{
			"playerId": "20521272",
			"username": "Vipraz",
			"stat": 108,
			"lastSeen": "2025-05-16T00:23:36.119253+00:00",
			"change": 0
		},
		{
			"playerId": "20736923",
			"username": "LonelyCrystalCabbage",
			"stat": 106,
			"lastSeen": "2025-05-12T12:23:45.125668+00:00",
			"change": 0
		},
		{
			"playerId": "18515317",
			"username": "cjohnston",
			"stat": 102,
			"lastSeen": "2025-05-15T16:38:00.194045+00:00",
			"change": 0
		},
		{
			"playerId": "9305740",
			"username": "Nhyiraba90",
			"stat": 99,
			"lastSeen": "2025-05-16T02:47:36.141534+00:00",
			"change": 0
		},
		{
			"playerId": "11856554",
			"username": "SleepyRubyGhoul",
			"stat": 98,
			"lastSeen": "2025-05-16T08:46:18.368144+00:00",
			"change": 0
		},
		{
			"playerId": "20738953",
			"username": "SmellyBetaBuzzSaw",
			"stat": 98,
			"lastSeen": "2025-05-13T00:47:45.193522+00:00",
			"change": 0
		},
		{
			"playerId": "20738954",
			"username": "LonelyDirtPixie",
			"stat": 98,
			"lastSeen": "2025-05-13T00:47:45.193522+00:00",
			"change": 0
		},
		{
			"playerId": "20437754",
			"username": "THORMART",
			"stat": 97,
			"lastSeen": "2025-05-16T07:13:27.372785+00:00",
			"change": 0
		},
		{
			"playerId": "20580684",
			"username": "InvisibleUltraPunch",
			"stat": 97,
			"lastSeen": "2025-05-15T23:32:36.126653+00:00",
			"change": 0
		},
		{
			"playerId": "20738955",
			"username": "LonelyDeluxeCookie",
			"stat": 96,
			"lastSeen": "2025-05-13T00:47:45.193522+00:00",
			"change": 0
		},
		{
			"playerId": "18570161",
			"username": "DrRalls",
			"stat": 95,
			"lastSeen": "2025-05-15T16:38:09.205577+00:00",
			"change": 0
		},
		{
			"playerId": "19848905",
			"username": "8Rax",
			"stat": 95,
			"lastSeen": "2025-05-16T11:23:36.367741+00:00",
			"change": 0
		},
		{
			"playerId": "20489398",
			"username": "JapaneseDenim",
			"stat": 95,
			"lastSeen": "2025-05-16T04:50:45.319041+00:00",
			"change": 0
		},
		{
			"playerId": "19629779",
			"username": "RainbowDash_9",
			"stat": 94,
			"lastSeen": "2025-05-16T11:27:45.374615+00:00",
			"change": 0
		},
		{
			"playerId": "18957527",
			"username": "MF_Zinc",
			"stat": 93,
			"lastSeen": "2025-05-15T15:17:09.366815+00:00",
			"change": 0
		},
		{
			"playerId": "3990108",
			"username": "Mandilindors",
			"stat": 93,
			"lastSeen": "2025-05-15T16:47:18.120820+00:00",
			"change": 0
		},
		{
			"playerId": "16281429",
			"username": "TheGreyman",
			"stat": 92,
			"lastSeen": "2025-05-15T14:48:27.138790+00:00",
			"change": 0
		},
		{
			"playerId": "20135735",
			"username": "BNeymarJR",
			"stat": 92,
			"lastSeen": "2025-05-15T12:31:00.055119+00:00",
			"change": 0
		},
		{
			"playerId": "20704013",
			"username": "LoneAcidSpringroll",
			"stat": 91,
			"lastSeen": "2025-05-16T02:24:09.130284+00:00",
			"change": 0
		},
		{
			"playerId": "19168800",
			"username": "ImmortalSteelPistol",
			"stat": 89,
			"lastSeen": "2025-05-15T17:34:18.131098+00:00",
			"change": 0
		},
		{
			"playerId": "20508106",
			"username": "Z-manTheIII",
			"stat": 86,
			"lastSeen": "2025-05-16T05:05:36.205217+00:00",
			"change": 0
		},
		{
			"playerId": "17362783",
			"username": "Enzizizin",
			"stat": 85,
			"lastSeen": "2025-05-15T21:27:09.129598+00:00",
			"change": 0
		},
		{
			"playerId": "20742123",
			"username": "LonelyFlameCommander",
			"stat": 85,
			"lastSeen": "2025-05-14T02:28:45.129156+00:00",
			"change": 0
		},
		{
			"playerId": "9156884",
			"username": "cronchyguac",
			"stat": 85,
			"lastSeen": "2025-05-16T03:16:54.318375+00:00",
			"change": 0
		},
		{
			"playerId": "12170137",
			"username": "SleepySpiritEagle",
			"stat": 84,
			"lastSeen": "2025-05-16T08:46:18.368144+00:00",
			"change": 0
		},
		{
			"playerId": "18749534",
			"username": "mlky",
			"stat": 84,
			"lastSeen": "2025-05-15T23:11:09.120590+00:00",
			"change": 0
		},
		{
			"playerId": "20137524",
			"username": "Qonca",
			"stat": 83,
			"lastSeen": "2025-05-15T11:14:45.367483+00:00",
			"change": 0
		},
		{
			"playerId": "12517909",
			"username": "Crip",
			"stat": 82,
			"lastSeen": "2025-05-14T05:49:54.156022+00:00",
			"change": 0
		},
		{
			"playerId": "10127129",
			"username": "Squeeze5",
			"stat": 81,
			"lastSeen": "2025-05-15T13:47:27.165841+00:00",
			"change": 0
		},
		{
			"playerId": "20445155",
			"username": "GLICH-BOY",
			"stat": 80,
			"lastSeen": "2025-05-16T00:51:00.195700+00:00",
			"change": 0
		},
		{
			"playerId": "8830881",
			"username": "xem",
			"stat": 80,
			"lastSeen": "2025-05-15T20:53:54.160311+00:00",
			"change": 0
		},
		{
			"playerId": "20592072",
			"username": "Umarconqueror1",
			"stat": 79,
			"lastSeen": "2025-05-15T19:47:27.372782+00:00",
			"change": 0
		},
		{
			"playerId": "13327781",
			"username": "rickgrimes",
			"stat": 78,
			"lastSeen": "2025-05-15T17:18:54.133803+00:00",
			"change": 0
		},
		{
			"playerId": "19873977",
			"username": "Lokai",
			"stat": 77,
			"lastSeen": "2025-05-16T09:58:00.363968+00:00",
			"change": 0
		},
		{
			"playerId": "20732893",
			"username": "LoneWaterSkeleton",
			"stat": 76,
			"lastSeen": "2025-05-15T06:56:36.323949+00:00",
			"change": 0
		},
		{
			"playerId": "18898438",
			"username": "FlorianGeyer",
			"stat": 74,
			"lastSeen": "2025-05-15T13:00:00.055667+00:00",
			"change": 0
		},
		{
			"playerId": "20314510",
			"username": "Tuan_Quang",
			"stat": 74,
			"lastSeen": "2025-05-16T07:09:00.373555+00:00",
			"change": 0
		},
		{
			"playerId": "4381511",
			"username": "interpreneur",
			"stat": 73,
			"lastSeen": "2025-05-15T21:16:54.124962+00:00",
			"change": 0
		},
		{
			"playerId": "19496050",
			"username": "ELBRAVO69",
			"stat": 72,
			"lastSeen": "2025-05-16T01:50:18.134225+00:00",
			"change": 0
		},
		{
			"playerId": "20380769",
			"username": "JGStockton",
			"stat": 72,
			"lastSeen": "2025-05-16T01:41:54.118618+00:00",
			"change": 0
		},
		{
			"playerId": "20637017",
			"username": "SuperSolar",
			"stat": 71,
			"lastSeen": "2025-05-16T11:14:45.377317+00:00",
			"change": 0
		},
		{
			"playerId": "6123238",
			"username": "Toastation",
			"stat": 70,
			"lastSeen": "2025-05-15T15:51:09.118182+00:00",
			"change": 0
		},
		{
			"playerId": "1975096",
			"username": "AL_B_SURE",
			"stat": 69,
			"lastSeen": "2025-05-16T01:40:36.189828+00:00",
			"change": 0
		},
		{
			"playerId": "4362539",
			"username": "DiscoVolante",
			"stat": 69,
			"lastSeen": "2025-05-16T11:13:27.123139+00:00",
			"change": 0
		},
		{
			"playerId": "20683205",
			"username": "LightFrostEye",
			"stat": 68,
			"lastSeen": "2025-05-15T18:51:36.180074+00:00",
			"change": 0
		},
		{
			"playerId": "20749799",
			"username": "ZanyPowerGryphon",
			"stat": 67,
			"lastSeen": "2025-05-16T03:45:27.192399+00:00",
			"change": 0
		},
		{
			"playerId": "20395730",
			"username": "HeroicGothWrecker",
			"stat": 66,
			"lastSeen": "2025-05-15T11:03:09.367911+00:00",
			"change": 0
		},
		{
			"playerId": "20637018",
			"username": "SpiderSrax",
			"stat": 66,
			"lastSeen": "2025-05-16T09:44:18.368200+00:00",
			"change": 0
		},
		{
			"playerId": "4191643",
			"username": "Etxrnity",
			"stat": 66,
			"lastSeen": "2025-05-16T01:48:18.152274+00:00",
			"change": 0
		},
		{
			"playerId": "20547490",
			"username": "SerbianEmpire",
			"stat": 65,
			"lastSeen": "2025-05-15T18:07:09.131487+00:00",
			"change": 0
		},
		{
			"playerId": "20727043",
			"username": "PurpleNecroClaw",
			"stat": 65,
			"lastSeen": "2025-05-15T00:44:00.059687+00:00",
			"change": 0
		},
		{
			"playerId": "20729929",
			"username": "Coolguyisoknice",
			"stat": 65,
			"lastSeen": "2025-05-15T21:11:27.187129+00:00",
			"change": 0
		},
		{
			"playerId": "2574833",
			"username": "voloding",
			"stat": 65,
			"lastSeen": "2025-05-15T19:43:45.134338+00:00",
			"change": 0
		},
		{
			"playerId": "20137703",
			"username": "FCMessi",
			"stat": 64,
			"lastSeen": "2025-05-16T11:27:45.127351+00:00",
			"change": 0
		},
		{
			"playerId": "20737009",
			"username": "BoomBoom",
			"stat": 64,
			"lastSeen": "2025-05-12T21:19:09.050853+00:00",
			"change": 0
		},
		{
			"playerId": "20737679",
			"username": "FH-mango",
			"stat": 64,
			"lastSeen": "2025-05-14T16:38:00.139440+00:00",
			"change": 0
		},
		{
			"playerId": "20742122",
			"username": "LonelyFireLemon",
			"stat": 64,
			"lastSeen": "2025-05-14T02:28:45.129156+00:00",
			"change": 0
		},
		{
			"playerId": "16735132",
			"username": "heckerwastaken",
			"stat": 63,
			"lastSeen": "2025-05-15T04:18:27.132138+00:00",
			"change": 0
		},
		{
			"playerId": "18898511",
			"username": "MoNsTeRkiller1",
			"stat": 63,
			"lastSeen": "2025-05-16T10:20:09.375127+00:00",
			"change": 0
		},
		{
			"playerId": "20725276",
			"username": "LoneSigma",
			"stat": 63,
			"lastSeen": "2025-05-15T07:44:18.063618+00:00",
			"change": 0
		}
	],
	"year": 2025,
	"month": 5,
	"week": 20
}