{
	"timestamp": "2025-10-18T16:04:55.099891+00:00",
	"data": [
		{
			"playerId": "6148530",
			"username": "Laika",
			"stat": 1247283,
			"lastSeen": "2025-10-18T16:04:54.374148+00:00",
			"change": 0
		},
		{
			"playerId": "19629780",
			"username": "twighlightSparles",
			"stat": 25931,
			"lastSeen": "2025-10-18T10:13:45.367403+00:00",
			"change": 0
		},
		{
			"playerId": "18418846",
			"username": "Blaze-X",
			"stat": 23028,
			"lastSeen": "2025-10-18T16:03:54.361164+00:00",
			"change": 0
		},
		{
			"playerId": "20731890",
			"username": "Rudy102",
			"stat": 18133,
			"lastSeen": "2025-10-17T22:33:00.056632+00:00",
			"change": 0
		},
		{
			"playerId": "20269995",
			"username": "Giffgaff224",
			"stat": 17908,
			"lastSeen": "2025-10-18T13:26:36.052679+00:00",
			"change": 0
		},
		{
			"playerId": "10127129",
			"username": "Squeeze5",
			"stat": 16516,
			"lastSeen": "2025-10-17T13:32:18.116088+00:00",
			"change": 0
		},
		{
			"playerId": "19768925",
			"username": "Lil_May",
			"stat": 16101,
			"lastSeen": "2025-10-18T11:39:09.062305+00:00",
			"change": 0
		},
		{
			"playerId": "8899024",
			"username": "PurpleSpaceBaboon",
			"stat": 16066,
			"lastSeen": "2025-10-18T02:34:27.114774+00:00",
			"change": 0
		},
		{
			"playerId": "2788716",
			"username": "YD109",
			"stat": 15832,
			"lastSeen": "2025-10-17T20:50:00.055896+00:00",
			"change": 0
		},
		{
			"playerId": "12331664",
			"username": "RedStrawBerry",
			"stat": 14788,
			"lastSeen": "2025-10-18T05:11:27.113647+00:00",
			"change": 0
		},
		{
			"playerId": "20445155",
			"username": "GLICH-BOY",
			"stat": 14592,
			"lastSeen": "2025-10-17T01:06:54.123491+00:00",
			"change": 0
		},
		{
			"playerId": "20691693",
			"username": "IDF",
			"stat": 13838,
			"lastSeen": "2025-10-17T23:25:18.189797+00:00",
			"change": 0
		},
		{
			"playerId": "13773720",
			"username": "Hafiz-Muhammad",
			"stat": 12551,
			"lastSeen": "2025-10-18T16:04:27.369332+00:00",
			"change": 0
		},
		{
			"playerId": "3660774",
			"username": "Sc4r",
			"stat": 12453,
			"lastSeen": "2025-10-18T05:11:00.120961+00:00",
			"change": 0
		},
		{
			"playerId": "19629779",
			"username": "RainbowDash_9",
			"stat": 12373,
			"lastSeen": "2025-10-18T16:04:09.371630+00:00",
			"change": 0
		},
		{
			"playerId": "20877041",
			"username": "LoyalFusionCheetah",
			"stat": 11660,
			"lastSeen": "2025-10-17T11:03:36.053175+00:00",
			"change": 0
		},
		{
			"playerId": "19635407",
			"username": "Mashin",
			"stat": 11483,
			"lastSeen": "2025-10-18T09:08:54.058626+00:00",
			"change": 0
		},
		{
			"playerId": "14892840",
			"username": "L_Shy_P",
			"stat": 11437,
			"lastSeen": "2025-10-18T11:49:27.364217+00:00",
			"change": 0
		},
		{
			"playerId": "20270104",
			"username": "3w0n",
			"stat": 10998,
			"lastSeen": "2025-10-18T13:28:27.064872+00:00",
			"change": 0
		},
		{
			"playerId": "8830881",
			"username": "xem",
			"stat": 10549,
			"lastSeen": "2025-10-18T13:54:27.057815+00:00",
			"change": 0
		},
		{
			"playerId": "20747321",
			"username": "skull999",
			"stat": 10484,
			"lastSeen": "2025-10-16T20:13:18.045025+00:00",
			"change": 0
		},
		{
			"playerId": "16337341",
			"username": "D_A_D",
			"stat": 10344,
			"lastSeen": "2025-10-18T05:06:27.116837+00:00",
			"change": 0
		},
		{
			"playerId": "17953682",
			"username": "hohi",
			"stat": 10104,
			"lastSeen": "2025-10-17T14:13:45.117990+00:00",
			"change": 0
		},
		{
			"playerId": "4381511",
			"username": "interpreneur",
			"stat": 9814,
			"lastSeen": "2025-10-17T23:26:09.124806+00:00",
			"change": 0
		},
		{
			"playerId": "18985660",
			"username": "volodymyr77",
			"stat": 9702,
			"lastSeen": "2025-10-18T16:04:54.190576+00:00",
			"change": 0
		},
		{
			"playerId": "16736853",
			"username": "SaucyReaper",
			"stat": 9527,
			"lastSeen": "2025-10-18T01:23:27.055223+00:00",
			"change": 0
		},
		{
			"playerId": "3024108",
			"username": "Sudoku",
			"stat": 9518,
			"lastSeen": "2025-10-17T19:11:18.058565+00:00",
			"change": 0
		},
		{
			"playerId": "19583686",
			"username": "Raxlyr",
			"stat": 9403,
			"lastSeen": "2025-10-17T17:19:09.364325+00:00",
			"change": 0
		},
		{
			"playerId": "17629928",
			"username": "_zenin_",
			"stat": 9209,
			"lastSeen": "2025-10-17T22:49:18.048512+00:00",
			"change": 0
		},
		{
			"playerId": "19059382",
			"username": "FantasticIronCabbage",
			"stat": 9055,
			"lastSeen": "2025-10-18T08:02:00.058672+00:00",
			"change": 0
		},
		{
			"playerId": "20637017",
			"username": "SuperSolar",
			"stat": 9022,
			"lastSeen": "2025-10-17T06:19:36.375966+00:00",
			"change": 0
		},
		{
			"playerId": "3990108",
			"username": "Mandilindors",
			"stat": 8528,
			"lastSeen": "2025-10-17T21:57:27.063387+00:00",
			"change": 0
		},
		{
			"playerId": "19458546",
			"username": "keraunoskiller",
			"stat": 8161,
			"lastSeen": "2025-10-18T12:36:36.382587+00:00",
			"change": 0
		},
		{
			"playerId": "20004968",
			"username": "NeatBlastTomato",
			"stat": 8016,
			"lastSeen": "2025-10-18T06:40:45.063220+00:00",
			"change": 0
		},
		{
			"playerId": "19201851",
			"username": "Noblesse",
			"stat": 7880,
			"lastSeen": "2025-10-18T03:48:27.116044+00:00",
			"change": 0
		},
		{
			"playerId": "20703867",
			"username": "s4ck4pht1",
			"stat": 7537,
			"lastSeen": "2025-10-16T23:49:09.145731+00:00",
			"change": 0
		},
		{
			"playerId": "18581516",
			"username": "JFLICK",
			"stat": 7525,
			"lastSeen": "2025-10-18T02:16:54.154404+00:00",
			"change": 0
		},
		{
			"playerId": "4191643",
			"username": "Etxrnity",
			"stat": 7493,
			"lastSeen": "2025-06-24T00:20:18.117984+00:00",
			"change": 0
		},
		{
			"playerId": "20380769",
			"username": "JGStockton",
			"stat": 7306,
			"lastSeen": "2025-10-16T22:55:54.053905+00:00",
			"change": 0
		},
		{
			"playerId": "13825931",
			"username": "Tigers786",
			"stat": 7209,
			"lastSeen": "2025-10-18T13:20:00.458733+00:00",
			"change": 0
		},
		{
			"playerId": "20801587",
			"username": "LooneyPhantomAnimal",
			"stat": 7015,
			"lastSeen": "2025-10-18T02:17:27.147349+00:00",
			"change": 0
		},
		{
			"playerId": "17629927",
			"username": "Beast",
			"stat": 6776,
			"lastSeen": "2025-10-16T19:23:09.056110+00:00",
			"change": 0
		},
		{
			"playerId": "17202244",
			"username": "HEROKILLUA99",
			"stat": 6707,
			"lastSeen": "2025-10-18T13:39:45.048892+00:00",
			"change": 0
		},
		{
			"playerId": "19425584",
			"username": "_Eddie_",
			"stat": 6698,
			"lastSeen": "2025-10-17T23:02:00.117277+00:00",
			"change": 0
		},
		{
			"playerId": "16347766",
			"username": "dark-x-prime",
			"stat": 6618,
			"lastSeen": "2025-10-18T12:43:00.060735+00:00",
			"change": 0
		},
		{
			"playerId": "12222122",
			"username": "SneakyOnyxDragon",
			"stat": 6280,
			"lastSeen": "2025-10-17T19:13:18.149866+00:00",
			"change": 0
		},
		{
			"playerId": "9465954",
			"username": "RaiIer",
			"stat": 6162,
			"lastSeen": "2025-10-17T09:55:45.370337+00:00",
			"change": 0
		},
		{
			"playerId": "20521272",
			"username": "Vipraz",
			"stat": 6017,
			"lastSeen": "2025-10-17T19:47:27.118043+00:00",
			"change": 0
		},
		{
			"playerId": "18898511",
			"username": "MoNsTeRkiller1",
			"stat": 5977,
			"lastSeen": "2025-10-18T13:02:45.448209+00:00",
			"change": 0
		},
		{
			"playerId": "20111777",
			"username": "Trizz",
			"stat": 5956,
			"lastSeen": "2025-10-18T11:48:45.050925+00:00",
			"change": 0
		},
		{
			"playerId": "20395730",
			"username": "KodumBheegaran",
			"stat": 5940,
			"lastSeen": "2025-10-17T07:53:36.370916+00:00",
			"change": 0
		},
		{
			"playerId": "19002763",
			"username": "Xyplexx",
			"stat": 5936,
			"lastSeen": "2025-10-18T05:11:27.113647+00:00",
			"change": 0
		},
		{
			"playerId": "8146384",
			"username": "itachi",
			"stat": 5805,
			"lastSeen": "2025-10-18T00:38:27.118075+00:00",
			"change": 0
		},
		{
			"playerId": "13327781",
			"username": "rickgrimes",
			"stat": 5701,
			"lastSeen": "2025-06-23T10:30:18.054869+00:00",
			"change": 0
		},
		{
			"playerId": "18625144",
			"username": "Orc-T72",
			"stat": 5670,
			"lastSeen": "2025-10-17T12:38:09.125999+00:00",
			"change": 0
		},
		{
			"playerId": "20642916",
			"username": "GOAT",
			"stat": 5649,
			"lastSeen": "2025-10-18T00:38:09.126390+00:00",
			"change": 0
		},
		{
			"playerId": "17120874",
			"username": "Kobi",
			"stat": 5543,
			"lastSeen": "2025-10-18T02:40:54.121798+00:00",
			"change": 0
		},
		{
			"playerId": "16596741",
			"username": "RawWarWarrior",
			"stat": 5541,
			"lastSeen": "2025-06-23T10:32:54.046834+00:00",
			"change": 0
		},
		{
			"playerId": "20843843",
			"username": "DNXR--gd",
			"stat": 5101,
			"lastSeen": "2025-10-18T13:41:18.448300+00:00",
			"change": 0
		},
		{
			"playerId": "16092601",
			"username": "fyrenado",
			"stat": 5053,
			"lastSeen": "2025-10-17T21:51:09.122593+00:00",
			"change": 0
		},
		{
			"playerId": "12128559",
			"username": "urdeadesa",
			"stat": 5048,
			"lastSeen": "2025-10-18T06:51:09.057740+00:00",
			"change": 0
		},
		{
			"playerId": "20883444",
			"username": "Supertank",
			"stat": 4954,
			"lastSeen": "2025-10-17T08:05:00.366352+00:00",
			"change": 0
		},
		{
			"playerId": "20074937",
			"username": "typeshhhhh",
			"stat": 4853,
			"lastSeen": "2025-10-17T16:28:45.043800+00:00",
			"change": 0
		},
		{
			"playerId": "17993161",
			"username": "StinkyFartPants",
			"stat": 4726,
			"lastSeen": "2025-10-18T09:55:45.360384+00:00",
			"change": 0
		},
		{
			"playerId": "20101050",
			"username": "Brainrot",
			"stat": 4637,
			"lastSeen": "2025-10-17T17:19:09.044710+00:00",
			"change": 0
		},
		{
			"playerId": "14752951",
			"username": "William14",
			"stat": 4451,
			"lastSeen": "2025-06-23T10:44:18.118642+00:00",
			"change": 0
		},
		{
			"playerId": "18749534",
			"username": "mlky",
			"stat": 4434,
			"lastSeen": "2025-06-24T00:02:45.118202+00:00",
			"change": 0
		},
		{
			"playerId": "20135735",
			"username": "BNeymarJR",
			"stat": 4432,
			"lastSeen": "2025-06-23T10:43:45.129579+00:00",
			"change": 0
		},
		{
			"playerId": "20616487",
			"username": "Layla9",
			"stat": 4422,
			"lastSeen": "2025-10-17T20:40:00.308871+00:00",
			"change": 0
		},
		{
			"playerId": "20643345",
			"username": "Musa_027",
			"stat": 4415,
			"lastSeen": "2025-06-23T10:17:36.046681+00:00",
			"change": 0
		},
		{
			"playerId": "2574833",
			"username": "voloding",
			"stat": 4201,
			"lastSeen": "2025-10-17T19:11:09.060868+00:00",
			"change": 0
		},
		{
			"playerId": "13783887",
			"username": "EPIC_GIRL",
			"stat": 4180,
			"lastSeen": "2025-10-18T12:40:36.453149+00:00",
			"change": 0
		},
		{
			"playerId": "20810949",
			"username": "LightPixie",
			"stat": 4157,
			"lastSeen": "2025-10-18T10:01:36.058447+00:00",
			"change": 0
		},
		{
			"playerId": "8590474",
			"username": "Novocaine",
			"stat": 4063,
			"lastSeen": "2025-06-23T20:56:45.118830+00:00",
			"change": 0
		},
		{
			"playerId": "16513004",
			"username": "BazooCachor4",
			"stat": 3993,
			"lastSeen": "2025-10-17T03:00:00.121137+00:00",
			"change": 0
		},
		{
			"playerId": "19600422",
			"username": "SmokyOnyxPeach",
			"stat": 3949,
			"lastSeen": "2025-10-17T14:32:09.049080+00:00",
			"change": 0
		},
		{
			"playerId": "20446747",
			"username": "ScratchAndSniff",
			"stat": 3939,
			"lastSeen": "2025-10-18T05:27:36.148514+00:00",
			"change": 0
		},
		{
			"playerId": "20704313",
			"username": "XxnoobxX",
			"stat": 3924,
			"lastSeen": "2025-06-22T18:36:36.128900+00:00",
			"change": 0
		},
		{
			"playerId": "18226906",
			"username": "Galatasaray",
			"stat": 3906,
			"lastSeen": "2025-10-18T09:24:45.058306+00:00",
			"change": 0
		},
		{
			"playerId": "20878918",
			"username": "Dealind",
			"stat": 3891,
			"lastSeen": "2025-10-18T10:45:18.368238+00:00",
			"change": 0
		},
		{
			"playerId": "18758912",
			"username": "SharpNitroPelican",
			"stat": 3820,
			"lastSeen": "2025-10-18T13:31:36.468314+00:00",
			"change": 0
		},
		{
			"playerId": "20875123",
			"username": "LoyalEarthGrenade",
			"stat": 3786,
			"lastSeen": "2025-10-18T09:17:27.122220+00:00",
			"change": 0
		},
		{
			"playerId": "9857606",
			"username": "Ira",
			"stat": 3779,
			"lastSeen": "2025-06-23T22:01:27.118975+00:00",
			"change": 0
		},
		{
			"playerId": "19691813",
			"username": "Jhxjan",
			"stat": 3654,
			"lastSeen": "2025-06-24T01:52:36.116622+00:00",
			"change": 0
		},
		{
			"playerId": "20852450",
			"username": "W4idenfeller",
			"stat": 3654,
			"lastSeen": "2025-10-17T12:44:36.046383+00:00",
			"change": 0
		},
		{
			"playerId": "19496050",
			"username": "ELBRAVO69",
			"stat": 3613,
			"lastSeen": "2025-10-16T18:58:27.198283+00:00",
			"change": 0
		},
		{
			"playerId": "18897513",
			"username": "unanimity",
			"stat": 3609,
			"lastSeen": "2025-10-18T03:39:09.117526+00:00",
			"change": 0
		},
		{
			"playerId": "20763798",
			"username": "Jason_Todd",
			"stat": 3595,
			"lastSeen": "2025-10-18T02:46:09.051915+00:00",
			"change": 0
		},
		{
			"playerId": "15931873",
			"username": "BeastVampireKiller",
			"stat": 3585,
			"lastSeen": "2025-10-18T01:56:00.052459+00:00",
			"change": 0
		},
		{
			"playerId": "20161033",
			"username": "GreyBabyWombat",
			"stat": 3550,
			"lastSeen": "2025-06-24T03:30:09.323010+00:00",
			"change": 0
		},
		{
			"playerId": "19726920",
			"username": "WillyWonkaBar",
			"stat": 3533,
			"lastSeen": "2025-10-18T12:15:09.447853+00:00",
			"change": 0
		},
		{
			"playerId": "18108574",
			"username": "ffgr",
			"stat": 3502,
			"lastSeen": "2025-06-13T13:50:18.054202+00:00",
			"change": 0
		},
		{
			"playerId": "12632496",
			"username": "Volta123",
			"stat": 3497,
			"lastSeen": "2025-10-17T15:08:09.367136+00:00",
			"change": 0
		},
		{
			"playerId": "20710649",
			"username": "Stuart",
			"stat": 3440,
			"lastSeen": "2025-10-18T01:08:18.126347+00:00",
			"change": 0
		},
		{
			"playerId": "4916090",
			"username": "Zys",
			"stat": 3427,
			"lastSeen": "2025-06-22T04:11:36.118175+00:00",
			"change": 0
		},
		{
			"playerId": "20858999",
			"username": "LousyProTwister",
			"stat": 3379,
			"lastSeen": "2025-06-24T01:29:45.118417+00:00",
			"change": 0
		},
		{
			"playerId": "9115125",
			"username": "HoneststrongTyphoon",
			"stat": 3352,
			"lastSeen": "2025-10-18T06:39:00.367763+00:00",
			"change": 0
		},
		{
			"playerId": "20314510",
			"username": "Tuan_Quang",
			"stat": 3330,
			"lastSeen": "2025-10-18T01:49:00.370606+00:00",
			"change": 0
		},
		{
			"playerId": "20137703",
			"username": "FCMessi",
			"stat": 3293,
			"lastSeen": "2025-06-23T10:27:36.060439+00:00",
			"change": 0
		},
		{
			"playerId": "8343413",
			"username": "II-ATC-II",
			"stat": 3227,
			"lastSeen": "2025-10-18T12:41:09.457349+00:00",
			"change": 0
		},
		{
			"playerId": "19168800",
			"username": "ImmortalSteelPistol",
			"stat": 3198,
			"lastSeen": "2025-10-17T16:06:00.118148+00:00",
			"change": 0
		}
	],
	"year": 2025
}