{
	"timestamp": "2025-06-14T22:49:55.100477+00:00",
	"data": [
		{
			"playerId": "6148530",
			"username": "Laika",
			"stat": 25170,
			"lastSeen": "2025-06-13T20:46:54.129972+00:00",
			"change": 0
		},
		{
			"playerId": "18418846",
			"username": "Blaze-X",
			"stat": 1401,
			"lastSeen": "2025-06-13T20:42:45.052874+00:00",
			"change": 0
		},
		{
			"playerId": "18108574",
			"username": "ffgr",
			"stat": 1085,
			"lastSeen": "2025-06-13T13:50:18.054202+00:00",
			"change": 0
		},
		{
			"playerId": "20161033",
			"username": "GreyBabyWombat",
			"stat": 967,
			"lastSeen": "2025-06-13T03:29:54.144153+00:00",
			"change": 0
		},
		{
			"playerId": "9115125",
			"username": "HoneststrongTyphoon",
			"stat": 901,
			"lastSeen": "2025-06-13T19:43:54.130289+00:00",
			"change": 0
		},
		{
			"playerId": "19629780",
			"username": "twighlightSparles",
			"stat": 864,
			"lastSeen": "2025-06-13T19:54:54.117225+00:00",
			"change": 0
		},
		{
			"playerId": "8899024",
			"username": "PurpleSpaceBaboon",
			"stat": 802,
			"lastSeen": "2025-06-13T20:27:00.128525+00:00",
			"change": 0
		},
		{
			"playerId": "10127129",
			"username": "Squeeze5",
			"stat": 770,
			"lastSeen": "2025-06-13T18:02:18.423416+00:00",
			"change": 0
		},
		{
			"playerId": "14752951",
			"username": "William14",
			"stat": 765,
			"lastSeen": "2025-06-13T18:22:54.061848+00:00",
			"change": 0
		},
		{
			"playerId": "20747321",
			"username": "skull999",
			"stat": 763,
			"lastSeen": "2025-06-13T12:10:54.066073+00:00",
			"change": 0
		},
		{
			"playerId": "20797941",
			"username": "YummyElectricStrike",
			"stat": 726,
			"lastSeen": "2025-06-13T15:43:45.051889+00:00",
			"change": 0
		},
		{
			"playerId": "18226906",
			"username": "GS_1905",
			"stat": 664,
			"lastSeen": "2025-06-13T18:16:09.053758+00:00",
			"change": 0
		},
		{
			"playerId": "20691693",
			"username": "Apex-Phantom",
			"stat": 661,
			"lastSeen": "2025-06-13T18:53:27.348051+00:00",
			"change": 0
		},
		{
			"playerId": "19458546",
			"username": "keraunoskiller",
			"stat": 638,
			"lastSeen": "2025-06-13T09:40:00.056105+00:00",
			"change": 0
		},
		{
			"playerId": "20269995",
			"username": "Giffgaff224",
			"stat": 488,
			"lastSeen": "2025-06-13T18:40:09.054767+00:00",
			"change": 0
		},
		{
			"playerId": "20788194",
			"username": "MOEHKDERNM",
			"stat": 479,
			"lastSeen": "2025-06-13T07:50:27.061853+00:00",
			"change": 0
		},
		{
			"playerId": "20234188",
			"username": "khak",
			"stat": 475,
			"lastSeen": "2025-06-13T05:57:09.068017+00:00",
			"change": 0
		},
		{
			"playerId": "4191643",
			"username": "Etxrnity",
			"stat": 456,
			"lastSeen": "2025-06-13T20:46:54.129972+00:00",
			"change": 0
		},
		{
			"playerId": "2788716",
			"username": "YD109",
			"stat": 448,
			"lastSeen": "2025-06-13T20:03:36.056452+00:00",
			"change": 0
		},
		{
			"playerId": "19629779",
			"username": "RainbowDash_9",
			"stat": 440,
			"lastSeen": "2025-06-13T12:54:00.061013+00:00",
			"change": 0
		},
		{
			"playerId": "16596741",
			"username": "RawWarWarrior",
			"stat": 436,
			"lastSeen": "2025-06-13T20:46:54.064000+00:00",
			"change": 0
		},
		{
			"playerId": "12331664",
			"username": "RedStrawBerry",
			"stat": 426,
			"lastSeen": "2025-06-13T05:24:18.143104+00:00",
			"change": 0
		},
		{
			"playerId": "20802396",
			"username": "6ix9ine",
			"stat": 409,
			"lastSeen": "2025-06-13T20:00:18.127726+00:00",
			"change": 0
		},
		{
			"playerId": "20713329",
			"username": "GreenDeath",
			"stat": 395,
			"lastSeen": "2025-06-13T19:43:36.058669+00:00",
			"change": 0
		},
		{
			"playerId": "20135735",
			"username": "BNeymarJR",
			"stat": 394,
			"lastSeen": "2025-06-13T17:49:27.055606+00:00",
			"change": 0
		},
		{
			"playerId": "16281429",
			"username": "TheGreyman",
			"stat": 370,
			"lastSeen": "2025-06-12T21:35:09.144940+00:00",
			"change": 0
		},
		{
			"playerId": "3660774",
			"username": "Sc4r",
			"stat": 369,
			"lastSeen": "2025-06-13T20:46:54.129972+00:00",
			"change": 0
		},
		{
			"playerId": "20822532",
			"username": "EF123",
			"stat": 368,
			"lastSeen": "2025-06-12T13:05:27.131383+00:00",
			"change": 0
		},
		{
			"playerId": "13773720",
			"username": "Hafiz-Muhammad",
			"stat": 367,
			"lastSeen": "2025-06-13T16:58:27.056711+00:00",
			"change": 0
		},
		{
			"playerId": "12745227",
			"username": "Sir_",
			"stat": 366,
			"lastSeen": "2025-06-13T09:27:09.124951+00:00",
			"change": 0
		},
		{
			"playerId": "19691813",
			"username": "Jhxjan",
			"stat": 365,
			"lastSeen": "2025-06-13T02:59:45.141745+00:00",
			"change": 0
		},
		{
			"playerId": "19840920",
			"username": "123killer786",
			"stat": 365,
			"lastSeen": "2025-06-13T12:30:18.065826+00:00",
			"change": 0
		},
		{
			"playerId": "20445155",
			"username": "GLICH-BOY",
			"stat": 346,
			"lastSeen": "2025-06-13T04:09:36.062592+00:00",
			"change": 0
		},
		{
			"playerId": "17089744",
			"username": "kitkat14",
			"stat": 337,
			"lastSeen": "2025-06-13T20:13:45.120351+00:00",
			"change": 0
		},
		{
			"playerId": "17629928",
			"username": "_zenin_",
			"stat": 332,
			"lastSeen": "2025-06-13T18:21:54.063414+00:00",
			"change": 0
		},
		{
			"playerId": "19657077",
			"username": "coifftretrau",
			"stat": 317,
			"lastSeen": "2025-06-12T05:09:27.377358+00:00",
			"change": 0
		},
		{
			"playerId": "20137703",
			"username": "FCMessi",
			"stat": 317,
			"lastSeen": "2025-06-13T17:41:18.061602+00:00",
			"change": 0
		},
		{
			"playerId": "13327781",
			"username": "rickgrimes",
			"stat": 314,
			"lastSeen": "2025-06-13T20:46:54.064000+00:00",
			"change": 0
		},
		{
			"playerId": "20643345",
			"username": "Musa_027",
			"stat": 305,
			"lastSeen": "2025-06-13T17:41:18.061602+00:00",
			"change": 0
		},
		{
			"playerId": "8590474",
			"username": "Novocaine",
			"stat": 304,
			"lastSeen": "2025-06-13T20:11:00.123670+00:00",
			"change": 0
		},
		{
			"playerId": "12517909",
			"username": "Crip",
			"stat": 301,
			"lastSeen": "2025-06-11T22:35:09.359688+00:00",
			"change": 0
		},
		{
			"playerId": "16736853",
			"username": "SaucyReaper",
			"stat": 297,
			"lastSeen": "2025-06-13T02:16:27.123155+00:00",
			"change": 0
		},
		{
			"playerId": "8830881",
			"username": "xem",
			"stat": 289,
			"lastSeen": "2025-06-13T19:15:45.055673+00:00",
			"change": 0
		},
		{
			"playerId": "18758912",
			"username": "SharpNitroPelican",
			"stat": 283,
			"lastSeen": "2025-06-12T05:34:45.361342+00:00",
			"change": 0
		},
		{
			"playerId": "17202244",
			"username": "HEROKILLUA99",
			"stat": 281,
			"lastSeen": "2025-06-13T18:07:09.058492+00:00",
			"change": 0
		},
		{
			"playerId": "19600422",
			"username": "SmokyOnyxPeach",
			"stat": 278,
			"lastSeen": "2025-06-13T18:07:54.057743+00:00",
			"change": 0
		},
		{
			"playerId": "19768925",
			"username": "Lil_May",
			"stat": 275,
			"lastSeen": "2025-06-13T18:46:00.128191+00:00",
			"change": 0
		},
		{
			"playerId": "29695",
			"username": "77777",
			"stat": 273,
			"lastSeen": "2025-06-13T15:54:18.133097+00:00",
			"change": 0
		},
		{
			"playerId": "4381511",
			"username": "interpreneur",
			"stat": 268,
			"lastSeen": "2025-06-13T20:05:09.057872+00:00",
			"change": 0
		},
		{
			"playerId": "13783887",
			"username": "EPIC_GIRL",
			"stat": 267,
			"lastSeen": "2025-06-12T13:33:18.053704+00:00",
			"change": 0
		},
		{
			"playerId": "20549294",
			"username": "ImTrAsHh",
			"stat": 263,
			"lastSeen": "2025-06-13T17:50:18.061755+00:00",
			"change": 0
		},
		{
			"playerId": "9857606",
			"username": "Ira",
			"stat": 262,
			"lastSeen": "2025-06-12T22:19:09.117664+00:00",
			"change": 0
		},
		{
			"playerId": "20270104",
			"username": "3w0n",
			"stat": 258,
			"lastSeen": "2025-06-13T18:21:09.126917+00:00",
			"change": 0
		},
		{
			"playerId": "3024108",
			"username": "Richard93973",
			"stat": 254,
			"lastSeen": "2025-06-13T18:27:18.058146+00:00",
			"change": 0
		},
		{
			"playerId": "20489398",
			"username": "JapaneseDenim",
			"stat": 249,
			"lastSeen": "2025-06-13T04:04:27.328378+00:00",
			"change": 0
		},
		{
			"playerId": "20781449",
			"username": "anhlong",
			"stat": 249,
			"lastSeen": "2025-06-05T11:32:18.366970+00:00",
			"change": 0
		},
		{
			"playerId": "18749534",
			"username": "mlky",
			"stat": 245,
			"lastSeen": "2025-06-12T00:16:09.057740+00:00",
			"change": 0
		},
		{
			"playerId": "20731890",
			"username": "Rudy102",
			"stat": 243,
			"lastSeen": "2025-06-07T20:49:45.252131+00:00",
			"change": 0
		},
		{
			"playerId": "13025142",
			"username": "Rvg3l",
			"stat": 242,
			"lastSeen": "2025-06-13T12:08:36.052521+00:00",
			"change": 0
		},
		{
			"playerId": "20784814",
			"username": "_tryhard_",
			"stat": 240,
			"lastSeen": "2025-06-13T16:26:09.164204+00:00",
			"change": 0
		},
		{
			"playerId": "16499473",
			"username": "thekiller12",
			"stat": 239,
			"lastSeen": "2025-06-13T19:48:00.050145+00:00",
			"change": 0
		},
		{
			"playerId": "17629927",
			"username": "Beast",
			"stat": 234,
			"lastSeen": "2025-06-13T19:05:18.064763+00:00",
			"change": 0
		},
		{
			"playerId": "20704313",
			"username": "XxnoobxX",
			"stat": 233,
			"lastSeen": "2025-06-12T01:34:09.146299+00:00",
			"change": 0
		},
		{
			"playerId": "19319642",
			"username": "deadromenss",
			"stat": 232,
			"lastSeen": "2025-06-13T20:46:54.064000+00:00",
			"change": 0
		},
		{
			"playerId": "3990108",
			"username": "Mandilindors",
			"stat": 232,
			"lastSeen": "2025-06-13T20:46:54.064000+00:00",
			"change": 0
		},
		{
			"playerId": "18898438",
			"username": "FlorianGeyer",
			"stat": 231,
			"lastSeen": "2025-06-12T10:06:00.061967+00:00",
			"change": 0
		},
		{
			"playerId": "20111151",
			"username": "Underground_I_kill_ya",
			"stat": 231,
			"lastSeen": "2025-06-12T18:25:45.056621+00:00",
			"change": 0
		},
		{
			"playerId": "20260577",
			"username": "HairyDoubleEagle",
			"stat": 231,
			"lastSeen": "2025-06-13T17:01:18.168135+00:00",
			"change": 0
		},
		{
			"playerId": "20703867",
			"username": "s4ck4pht1",
			"stat": 229,
			"lastSeen": "2025-06-13T02:31:45.123782+00:00",
			"change": 0
		},
		{
			"playerId": "16347766",
			"username": "dark-x-prime",
			"stat": 228,
			"lastSeen": "2025-06-13T20:46:00.128003+00:00",
			"change": 0
		},
		{
			"playerId": "17120874",
			"username": "Kobi",
			"stat": 226,
			"lastSeen": "2025-06-12T03:53:45.121094+00:00",
			"change": 0
		},
		{
			"playerId": "12316356",
			"username": "firekingPunch",
			"stat": 225,
			"lastSeen": "2025-06-13T19:18:36.069207+00:00",
			"change": 0
		},
		{
			"playerId": "11808256",
			"username": "xXxxvxxXx",
			"stat": 222,
			"lastSeen": "2025-06-11T23:23:00.121715+00:00",
			"change": 0
		},
		{
			"playerId": "17362783",
			"username": "Enzizizin",
			"stat": 221,
			"lastSeen": "2025-06-13T01:47:27.117358+00:00",
			"change": 0
		},
		{
			"playerId": "17993161",
			"username": "StinkyFartPants",
			"stat": 221,
			"lastSeen": "2025-06-13T10:24:54.337166+00:00",
			"change": 0
		},
		{
			"playerId": "10523030",
			"username": "DIMIG0D",
			"stat": 218,
			"lastSeen": "2025-06-13T19:58:09.121395+00:00",
			"change": 0
		},
		{
			"playerId": "19597264",
			"username": "ICEAXE",
			"stat": 215,
			"lastSeen": "2025-06-13T20:41:27.061865+00:00",
			"change": 0
		},
		{
			"playerId": "20581942",
			"username": "_---THE-TITANK-ANIKILATOR",
			"stat": 211,
			"lastSeen": "2025-06-13T19:57:18.061226+00:00",
			"change": 0
		},
		{
			"playerId": "9156884",
			"username": "cronchyguac",
			"stat": 209,
			"lastSeen": "2025-06-13T00:04:36.328681+00:00",
			"change": 0
		},
		{
			"playerId": "12128559",
			"username": "urdeadesa",
			"stat": 208,
			"lastSeen": "2025-06-11T23:52:27.057273+00:00",
			"change": 0
		},
		{
			"playerId": "7326540",
			"username": "Hot_shot",
			"stat": 208,
			"lastSeen": "2025-06-11T22:06:45.062330+00:00",
			"change": 0
		},
		{
			"playerId": "17609168",
			"username": "blackkingogo",
			"stat": 206,
			"lastSeen": "2025-06-05T16:21:45.368074+00:00",
			"change": 0
		},
		{
			"playerId": "20785332",
			"username": "Fleece",
			"stat": 206,
			"lastSeen": "2025-06-13T19:35:09.062701+00:00",
			"change": 0
		},
		{
			"playerId": "20268396",
			"username": "sheff",
			"stat": 204,
			"lastSeen": "2025-06-13T05:52:27.124842+00:00",
			"change": 0
		},
		{
			"playerId": "20754942",
			"username": "Kr-Drek",
			"stat": 200,
			"lastSeen": "2025-06-12T13:53:36.065958+00:00",
			"change": 0
		},
		{
			"playerId": "19353162",
			"username": "fearsomeflamespunk",
			"stat": 199,
			"lastSeen": "2025-06-12T10:49:09.332901+00:00",
			"change": 0
		},
		{
			"playerId": "20137524",
			"username": "Qonca",
			"stat": 195,
			"lastSeen": "2025-06-13T15:20:27.063046+00:00",
			"change": 0
		},
		{
			"playerId": "17409397",
			"username": "GoldTankNoob",
			"stat": 194,
			"lastSeen": "2025-06-07T15:06:37.679917+00:00",
			"change": 0
		},
		{
			"playerId": "20524819",
			"username": "BL00D_GLICH",
			"stat": 193,
			"lastSeen": "2025-06-11T20:54:18.116136+00:00",
			"change": 0
		},
		{
			"playerId": "19938893",
			"username": "CsokiAron",
			"stat": 191,
			"lastSeen": "2025-06-12T12:07:36.062832+00:00",
			"change": 0
		},
		{
			"playerId": "18898511",
			"username": "MoNsTeRkiller1",
			"stat": 187,
			"lastSeen": "2025-06-07T15:22:09.373517+00:00",
			"change": 0
		},
		{
			"playerId": "19657105",
			"username": "taolavuakind",
			"stat": 184,
			"lastSeen": "2025-06-12T05:09:27.377358+00:00",
			"change": 0
		},
		{
			"playerId": "20033275",
			"username": "MMHV",
			"stat": 183,
			"lastSeen": "2025-06-12T08:06:45.126088+00:00",
			"change": 0
		},
		{
			"playerId": "12572965",
			"username": "vcxiumtms",
			"stat": 182,
			"lastSeen": "2025-06-12T19:11:45.072180+00:00",
			"change": 0
		},
		{
			"playerId": "20795619",
			"username": "Shiraz",
			"stat": 179,
			"lastSeen": "2025-06-13T04:15:18.059311+00:00",
			"change": 0
		},
		{
			"playerId": "4686507",
			"username": "playboi",
			"stat": 177,
			"lastSeen": "2025-06-12T01:47:54.055482+00:00",
			"change": 0
		},
		{
			"playerId": "18147404",
			"username": "THEPROAZO",
			"stat": 176,
			"lastSeen": "2025-06-12T10:50:18.055190+00:00",
			"change": 0
		},
		{
			"playerId": "20815429",
			"username": "WackyUltraT-Rex",
			"stat": 176,
			"lastSeen": "2025-06-05T11:00:36.053882+00:00",
			"change": 0
		},
		{
			"playerId": "17953682",
			"username": "hohi",
			"stat": 175,
			"lastSeen": "2025-06-13T16:37:54.135186+00:00",
			"change": 0
		},
		{
			"playerId": "20405991",
			"username": "Gr4peApe",
			"stat": 171,
			"lastSeen": "2025-06-11T18:02:36.062797+00:00",
			"change": 0
		},
		{
			"playerId": "20380769",
			"username": "JGStockton",
			"stat": 169,
			"lastSeen": "2025-06-12T22:46:36.128654+00:00",
			"change": 0
		}
	],
	"year": 2025,
	"month": 6
}